README.md
setup.cfg
setup.py
jenkinsc/__init__.py
jenkinsc/jenkins.py
jenkinsc/test_utils.py
jenkinsc/utils.py
jenkinsc.egg-info/PKG-INFO
jenkinsc.egg-info/SOURCES.txt
jenkinsc.egg-info/dependency_links.txt
jenkinsc.egg-info/top_level.txt