Metadata-Version: 2.1
Name: jenkinsc
Version: 0.0.38
Summary: bulletproof jenkins client
Home-page: https://github.com/ahcub/jenkinsc
Author: Alex Buchkovsky
Author-email: olex.buchkovsky@gmail.com
License: UNKNOWN
Keywords: jenkins,automation,ci,client,python
Platform: UNKNOWN
